{"cameraMode":{"drawMode":0,"name":"Shaded","section":"Shading Mode"},"sceneLighting":false,"audioPlay":false,"sceneViewState":{"m_AlwaysRefresh":false,"showFog":true,"showSkybox":false,"showFlares":true,"showImageEffects":true,"showParticleSystems":true,"showVisualEffectGraphs":true,"m_FxEnabled":true},"in2DMode":false,"pivot":{"x":-7.175098419189453,"y":-103.78602600097656,"z":-8.299057006835938},"rotation":{"x":-0.02551356703042984,"y":0.9595565795898438,"z":-0.26603466272354128,"w":-0.09067077189683914},"size":110.12913513183594,"orthographic":false}